rqt_record/__init__.py
rqt_record/main.py
rqt_record/rqt_main.py
rqt_record-0.0.1.dist-info/LICENSE
rqt_record-0.0.1.dist-info/METADATA
rqt_record-0.0.1.dist-info/WHEEL
rqt_record-0.0.1.dist-info/entry_points.txt
rqt_record-0.0.1.dist-info/top_level.txt
rqt_record-0.0.1.dist-info/RECORD
